pyg_base/__init__.py
pyg_base/_as_float.py
pyg_base/_as_list.py
pyg_base/_as_primitive.py
pyg_base/_bitemporal.py
pyg_base/_cache.py
pyg_base/_cfg.py
pyg_base/_dates.py
pyg_base/_decorators.py
pyg_base/_dict.py
pyg_base/_dictable.py
pyg_base/_dictattr.py
pyg_base/_drange.py
pyg_base/_eq.py
pyg_base/_file.py
pyg_base/_getitem.py
pyg_base/_inspect.py
pyg_base/_interp.py
pyg_base/_logger.py
pyg_base/_loop.py
pyg_base/_named_dict.py
pyg_base/_pandas.py
pyg_base/_perdictable.py
pyg_base/_reducer.py
pyg_base/_roll.py
pyg_base/_sort.py
pyg_base/_table_to_tree.py
pyg_base/_tenor.py
pyg_base/_tree.py
pyg_base/_tree_repr.py
pyg_base/_txt.py
pyg_base/_types.py
pyg_base/_ulist.py
pyg_base/_unique.py
pyg_base/_waiter.py
pyg_base/_xls.py
pyg_base/_zip.py
pyg_base-0.0.99.dist-info/licenses/LICENSE.txt
pyg_base-0.0.99.dist-info/METADATA
pyg_base-0.0.99.dist-info/WHEEL
pyg_base-0.0.99.dist-info/top_level.txt
pyg_base-0.0.99.dist-info/RECORD
