Metadata-Version: 2.4
Name: pyg-base
Version: 0.0.99
Summary: Utilities for data manipulation including creation of DAGs and tables
Home-page: https://github.com/gityoav/pyg-base
Author: Yoav Git
Author-email: yoav.git@gmail.com
Project-URL: Bug Tracker, https://github.com/gityoav/pyg-base/issues
Classifier: Programming Language :: Python :: 3
Classifier: License :: OSI Approved :: GNU General Public License v3 (GPLv3)
Classifier: Operating System :: OS Independent
Requires-Python: >=3.6
License-File: LICENSE.txt
Requires-Dist: numpy
Requires-Dist: scipy
Requires-Dist: pandas
Requires-Dist: jsonpickle
Dynamic: license-file
